windio_converter/__init__.py
windio_converter/common.py
windio_converter/utils.py
windio_converter/from_windio/__init__.py
windio_converter/from_windio/hawc2/__init__.py
windio_converter/from_windio/hawc2/ae.py
windio_converter/from_windio/hawc2/common.py
windio_converter/from_windio/hawc2/pc.py
windio_converter/from_windio/hawc2/htc/__init__.py
windio_converter/from_windio/hawc2/htc/aero_hydro.py
windio_converter/from_windio/hawc2/htc/dll/__init__.py
windio_converter/from_windio/hawc2/htc/dll/type2_dll/__init__.py
windio_converter/from_windio/hawc2/htc/dll/type2_dll/dtu_we_controller.py
windio_converter/from_windio/hawc2/htc/new_htc_structure/__init__.py
windio_converter/from_windio/hawc2/htc/new_htc_structure/common.py
windio_converter/from_windio/hawc2/htc/new_htc_structure/ext_sys.py
windio_converter/from_windio/hawc2/htc/new_htc_structure/constraints/__init__.py
windio_converter/from_windio/hawc2/htc/new_htc_structure/constraints/bearing.py
windio_converter/from_windio/hawc2/htc/new_htc_structure/constraints/fix.py
windio_converter/from_windio/hawc2/htc/new_htc_structure/constraints/mooring.py
windio_converter/from_windio/hawc2/htc/new_htc_structure/main_body/__init__.py
windio_converter/from_windio/hawc2/htc/new_htc_structure/main_body/blade.py
windio_converter/from_windio/hawc2/htc/new_htc_structure/main_body/common.py
windio_converter/from_windio/hawc2/htc/new_htc_structure/main_body/floating_platform.py
windio_converter/from_windio/hawc2/htc/new_htc_structure/main_body/monopile.py
windio_converter/from_windio/hawc2/htc/new_htc_structure/main_body/shaft.py
windio_converter/from_windio/hawc2/htc/new_htc_structure/main_body/simple_bodies.py
windio_converter/from_windio/hawc2/htc/new_htc_structure/main_body/tower.py
windio_converter/from_windio/hawc2/htc/new_htc_structure/main_body/towertop.py
windio_converter/from_windio/hawc2/htc/new_htc_structure/orientation/__init__.py
windio_converter/from_windio/hawc2/htc/new_htc_structure/orientation/base.py
windio_converter-0.2.8.dist-info/licenses/LICENSE
windio_converter-0.2.8.dist-info/METADATA
windio_converter-0.2.8.dist-info/WHEEL
windio_converter-0.2.8.dist-info/top_level.txt
windio_converter-0.2.8.dist-info/RECORD
