Metadata-Version: 2.4
Name: windio_converter
Version: 0.2.8
Author-email: Kenneth Loenbaek <kenloen@dtu.dk>
Maintainer-email: Kenneth Loenbaek <kenloen@dtu.dk>
License: MIT License
Project-URL: DTU-Wind-Gitlab, https://gitlab.windenergy.dtu.dk/AESOpt/windio-converter
Project-URL: Documentation, https://aesopt.pages.windenergy.dtu.dk/windio-converter
License-File: LICENSE
Requires-Dist: numpy
Requires-Dist: scipy
Requires-Dist: jmespath
Requires-Dist: ruamel.yaml
Requires-Dist: aesoptparam
Provides-Extra: test
Requires-Dist: pytest; extra == "test"
Requires-Dist: pytest-cov; extra == "test"
Requires-Dist: isort; extra == "test"
Requires-Dist: black; extra == "test"
Requires-Dist: wetb; extra == "test"
Provides-Extra: docs
Requires-Dist: sphinx; extra == "docs"
Requires-Dist: sphinx-design; extra == "docs"
Requires-Dist: sphinx_book_theme; extra == "docs"
Requires-Dist: myst-parser; extra == "docs"
Requires-Dist: sphinx_external_toc; extra == "docs"
Requires-Dist: sphinxcontrib.bibtex; extra == "docs"
Requires-Dist: myst-nb; extra == "docs"
Requires-Dist: markdown; extra == "docs"
Requires-Dist: jupytext; extra == "docs"
Requires-Dist: setuptools; extra == "docs"
Requires-Dist: matplotlib; extra == "docs"
Provides-Extra: all
Requires-Dist: windio_converter[docs,test]; extra == "all"
Dynamic: license-file
